httpaste/__init__.py
httpaste/__main__.py
httpaste/cgi.py
httpaste/fcgi.py
httpaste/wsgi.py
httpaste/backend/__init__.py
httpaste/backend/file/__init__.py
httpaste/backend/file/paste.py
httpaste/backend/file/user.py
httpaste/backend/sqlite/__init__.py
httpaste/backend/sqlite/paste.py
httpaste/backend/sqlite/paste.sql
httpaste/backend/sqlite/user.py
httpaste/backend/sqlite/user.sql
httpaste/controller/__init__.py
httpaste/controller/paste/__init__.py
httpaste/controller/paste/private.py
httpaste/controller/paste/public.py
httpaste/controller/user/__init__.py
httpaste/controller/user/session.py
httpaste/helper/__init__.py
httpaste/helper/common.py
httpaste/helper/crypto.py
httpaste/helper/http.py
httpaste/helper/syntax.py
httpaste/model/__init__.py
httpaste/model/paste.py
httpaste/model/user.py
httpaste/schema/__init__.py
httpaste/schema/httpaste.openapi.json
httpaste_victorykit-1.0.13a0.dist-info/LICENSE
httpaste_victorykit-1.0.13a0.dist-info/METADATA
httpaste_victorykit-1.0.13a0.dist-info/WHEEL
httpaste_victorykit-1.0.13a0.dist-info/entry_points.txt
httpaste_victorykit-1.0.13a0.dist-info/top_level.txt
httpaste_victorykit-1.0.13a0.dist-info/zip-safe
httpaste_victorykit-1.0.13a0.dist-info/RECORD
