Metadata-Version: 2.1
Name: httpaste-victorykit
Version: 1.0.13a0
Summary: a versatile HTTP pastebin
Home-page: https://victorykit.bitbucket.io/httpaste
Author: Tiara Rodney
Author-email: t.rodney@victoryk.it
License: UNKNOWN
Project-URL: Bug Tracker, https://bitbucket.org/victorykit/httpaste/jira
Platform: UNKNOWN
Classifier: Development Status :: 3 - Alpha
Classifier: Intended Audience :: Developers
Classifier: Topic :: Internet :: WWW/HTTP :: WSGI :: Server
Classifier: Programming Language :: Python :: 3.7
Classifier: Programming Language :: Python :: 3.8
Classifier: Programming Language :: Python :: 3.9
Classifier: Operating System :: OS Independent
Classifier: License :: OSI Approved :: GNU General Public License v3 or later (GPLv3+)
Requires-Python: >=3.7
License-File: LICENSE
Requires-Dist: connexion (<3,>=2.13.0)
Requires-Dist: cryptography (<37,>=36.0.2)
Requires-Dist: pygments (<3,>=2.11.2)
